donzo_cmd/__init__.py
donzo_cmd/cmd.py
donzo_cmd-0.1.4.dist-info/METADATA
donzo_cmd-0.1.4.dist-info/WHEEL
donzo_cmd-0.1.4.dist-info/top_level.txt
donzo_cmd-0.1.4.dist-info/RECORD
