Metadata-Version: 2.1
Name: donzo_cmd
Version: 0.1.4
Summary: Default template for PDM package
Author-email: mangG907 <mang.gee@gmail.com>
License: MIT
Project-URL: Homepage,  https://github.com/mangG907/donzo_cmd
Project-URL: Issues, https://github.com/mangG907/donzo_cmd/issues
Requires-Python: >=3.9
Requires-Dist: donzo-plus >=0.1.5
Requires-Dist: donzo-multiple >=0.1.4
Requires-Dist: donzo-divide >=0.1.1
